auto_rest/__init__.py
auto_rest/apps.py
auto_rest/urls.py
auto_rest/views.py
django_auto_rest-0.2.1.dist-info/LICENSE
django_auto_rest-0.2.1.dist-info/METADATA
django_auto_rest-0.2.1.dist-info/WHEEL
django_auto_rest-0.2.1.dist-info/top_level.txt
django_auto_rest-0.2.1.dist-info/RECORD
