Metadata-Version: 2.1
Name: django-auto-rest
Version: 0.2.1
Summary: an automatic REST API for all the models in a Django project
Home-page: https://github.com/olegkishenkov/django-auto-rest
Author: olegkishenkov
Author-email: oleg.kishenkov@gmail.com
Classifier: Programming Language :: Python :: 3
Classifier: License :: OSI Approved :: MIT License
Classifier: Operating System :: OS Independent
Requires-Python: >=3.8
License-File: LICENSE
